cbors-0.1.4.dist-info/METADATA
cbors-0.1.4.dist-info/WHEEL
cbors.cpython-38-x86_64-linux-gnu.so
cbors-0.1.4.dist-info/RECORD
