Metadata-Version: 2.1
Name: cbors
Version: 0.1.4
Classifier: Development Status :: 4 - Beta
Classifier: Intended Audience :: Developers
Classifier: License :: OSI Approved :: MIT License
Classifier: Programming Language :: Python :: 3 :: Only
Classifier: Programming Language :: Python :: 3.5
Classifier: Programming Language :: Python :: 3.6
Classifier: Programming Language :: Python :: 3.7
Summary: A Python CBOR (de)serialization module, powered by Rust
Keywords: cbor serialization deserialization python
Home-Page: https://github.com/mjkoo/cbors
Author: Maxwell Koo <mjkoo90@gmail.com>
Author-Email: Maxwell Koo <mjkoo90@gmail.com>
License: MIT
